sampling_utils/__init__.py
sampling_utils/helper_functions.py
sampling_utils/sampling_functions.py
sampling_utils-0.1.1.dist-info/LICENCE
sampling_utils-0.1.1.dist-info/METADATA
sampling_utils-0.1.1.dist-info/WHEEL
sampling_utils-0.1.1.dist-info/top_level.txt
sampling_utils-0.1.1.dist-info/RECORD
