Metadata-Version: 2.1
Name: sampling-utils
Version: 0.1.1
Summary: Python tools to sample randomly with dont pick closest `n` elements constraints. Also contains a batch generator for the same to sample with replacement and with repeats if necessary.
Home-page: https://github.com/saravanabalagi/sampling_utils
Author: Saravanabalagi Ramachandran
Author-email: saravanabalagi@hotmail.com
License: MIT
Platform: UNKNOWN
Classifier: Development Status :: 4 - Beta
Classifier: Topic :: Software Development :: Libraries
Classifier: License :: OSI Approved :: MIT License
Classifier: Programming Language :: Python :: 3
Classifier: Programming Language :: Python :: 3.6
Classifier: Programming Language :: Python :: 3.7
Requires-Dist: numpy
